iflow_mcp_dnd_mcp-0.1.0.dist-info/licenses/LICENSE
src/__init__.py
src/attribution/__init__.py
src/attribution/citation.py
src/attribution/confidence.py
src/attribution/core.py
src/attribution/formatters.py
src/attribution/source_tracking.py
src/attribution/tool_tracking.py
src/core/__init__.py
src/core/api_helpers.py
src/core/cache.py
src/core/formatters.py
src/core/prompts.py
src/core/resources.py
src/core/tools.py
src/query_enhancement/__init__.py
src/query_enhancement/category_prioritization.py
src/query_enhancement/fuzzy_matching.py
src/query_enhancement/synonyms.py
src/query_enhancement/tokenizer.py
src/templates/__init__.py
src/templates/config.py
src/templates/equipment.py
src/templates/formatter.py
src/templates/monster.py
src/templates/spell.py
tests/__init__.py
tests/test_attribution.py
tests/test_mcp_attribution.py
tests/test_query_enhancement.py
tests/test_search_enhancement.py
tests/test_template_integration.py
tests/test_templates.py
iflow_mcp_dnd_mcp-0.1.0.dist-info/METADATA
iflow_mcp_dnd_mcp-0.1.0.dist-info/WHEEL
iflow_mcp_dnd_mcp-0.1.0.dist-info/entry_points.txt
iflow_mcp_dnd_mcp-0.1.0.dist-info/top_level.txt
iflow_mcp_dnd_mcp-0.1.0.dist-info/RECORD
