Metadata-Version: 2.4
Name: iflow-mcp_dnd-mcp
Version: 0.1.0
Summary: Add your description here
Author: D&D Knowledge Navigator Contributors
Author-email: your.email@example.com
Requires-Python: >=3.10
License-File: LICENSE
Requires-Dist: httpx>=0.28.1
Requires-Dist: mcp>=1.3.0
Dynamic: author
Dynamic: author-email
Dynamic: license-file
Dynamic: requires-python
